katalytic/maths/__init__.py
katalytic/maths/bboxes.py
katalytic_maths-0.2.2.dist-info/LICENSE.txt
katalytic_maths-0.2.2.dist-info/WHEEL
katalytic_maths-0.2.2.dist-info/METADATA
katalytic_maths-0.2.2.dist-info/RECORD
