Metadata-Version: 2.1
Name: katalytic-maths
Version: 0.2.2
Summary: This plugin adds utilities for mathematical tasks
Author-email: Valentin Neagu <vali19th@protonmail.com>
Requires-Python: >=3.6
Classifier: Development Status :: 3 - Alpha
Classifier: Intended Audience :: Developers
Classifier: Intended Audience :: Science/Research
Classifier: License :: OSI Approved :: MIT License
Classifier: Natural Language :: English
Classifier: Operating System :: OS Independent
Classifier: Programming Language :: Python :: 3
Classifier: Topic :: Scientific/Engineering :: Mathematics
Classifier: Topic :: Scientific/Engineering
Classifier: Topic :: Software Development :: Libraries
Classifier: Topic :: Utilities
Requires-Dist: katalytic-data>=0.9.0
Requires-Dist: katalytic-pkg>=0.4.0
Requires-Dist: pytest ; extra == "dev"
Requires-Dist: pytest-cov ; extra == "dev"
Requires-Dist: pytest-clarity ; extra == "dev"
Requires-Dist: pytest-randomly ; extra == "dev"
Project-URL: homepage, https://gitlab.com/katalytic/katalytic-maths.git
Project-URL: repository, https://gitlab.com/katalytic/katalytic-maths.git
Provides-Extra: dev
